README
setup.py
dyno/__init__.py
dyno/__main__.py
dyno/aspect.py
dyno/breaker.py
dyno/cache.py
dyno/harness.py
dyno/injection.py
dyno/metrics.py
dyno/registry.py
dyno/retry.py
dyno/service.py
dyno/timing.py
dyno/utils.py
dyno.egg-info/PKG-INFO
dyno.egg-info/SOURCES.txt
dyno.egg-info/dependency_links.txt
dyno.egg-info/requires.txt
dyno.egg-info/top_level.txt
dyno.egg-info/zip-safe