Metadata-Version: 1.1
Name: dyno
Version: 0.1
Summary: Dependency injection framework based of Netflix's Hystrix
Home-page: http://code.pocketnix.org/dyno
Author: Da_Blitz
Author-email: code@pocketnix.org
License: MIT BSD
Download-URL: ['http://code.pocketnix.org/dyno/archive/tip.tar.bz2', 'http://code.pocketnix.org/dyno/archive/tip.tar.gzhttp://code.pocketnix.org/dyno/archive/tip.zip']
Keywords: DI dependency injection framework hystrix guice
Platform: UNKNOWN
